chillin_client/__init__.py
chillin_client/ais.py
chillin_client/config.py
chillin_client/core.py
chillin_client/network.py
chillin_client/protocol.py
chillin_client/helpers/__init__.py
chillin_client/helpers/datetime.py
chillin_client/helpers/logger.py
chillin_client/helpers/messages.py
chillin_client/helpers/parser.py
chillin_client/helpers/singleton.py
chillin_client-1.3.1.dist-info/DESCRIPTION.rst
chillin_client-1.3.1.dist-info/METADATA
chillin_client-1.3.1.dist-info/RECORD
chillin_client-1.3.1.dist-info/WHEEL
chillin_client-1.3.1.dist-info/metadata.json
chillin_client-1.3.1.dist-info/top_level.txt
