Metadata-Version: 1.1
Name: chillin-client
Version: 1.3.1
Summary: Chillin AI Game Framework (Python Client)
Home-page: https://github.com/koala-team/Chillin-PyClient
Author: Koala
Author-email: mdan.hagh@gmail.com
License: AGPL License, Version 3.0
Keywords: ai game framework chillin
Platform: UNKNOWN
Classifier: Environment :: Console
Classifier: License :: OSI Approved :: GNU Affero General Public License v3
Classifier: Intended Audience :: Developers
Classifier: Operating System :: OS Independent
Classifier: Programming Language :: Python :: 2.7
Classifier: Programming Language :: Python :: 3.5
Classifier: Topic :: Software Development :: Libraries :: Application Frameworks
